{"projects": [{"project_id": 1, "name": "Delta 100 CS", "description": "General pesticide project", "tasks": [{"task_id": 1, "title": "Resolve SYN Negotiation", "description": "SYN will not negotiate with us. Finding alternative suppliers due to isomer content.", "status": "On hold", "assigned_to": "Jane"}, {"task_id": 2, "title": "Legal Proceedings", "description": "Decision taken not to take SYN to court. Exploring other options.", "status": "Completed", "assigned_to": "Dave"}, {"task_id": null, "name": "", "description": "", "status": "On hold"}]}, {"project_id": 2, "name": "Rothio/Etco (Art. 33 with 2nd year of field trial data)", "description": "Russian Federation pesticide project", "tasks": [{"task_id": 1, "title": "Completeness Check", "description": "Completeness check received for application with 2nd year efficacy trials.", "status": "In progress", "assigned_to": "Emily"}, {"task_id": 2, "title": "TDM Feedback", "description": "Awaiting TDM feedback before deciding on the next steps for the application.", "status": "Awaiting Response", "assigned_to": "Mike"}]}, {"project_id": 3, "name": "Rothio/Etco", "description": "Czech Republic and FDR pesticide project", "tasks": [{"task_id": 1, "title": "Address FDR Evaluation", "description": "FDR had many comments on dRR. Stated efficacy unacceptable for all uses except rust on wheat.", "status": "In Review", "assigned_to": "Laura"}, {"task_id": 2, "title": "CZ Authorization", "description": "Submit ambient storage stability post-authorization in CZ.", "status": "Completed", "assigned_to": "John"}]}, {"project_id": 4, "name": "Rothio/Etco (MR from CZ)", "description": "Multi-country pesticide project", "tasks": [{"task_id": 1, "title": "PL Dossier Preparation", "description": "Dossier preparation for submission in Poland. Submission expected in early July 2023.", "status": "In progress", "assigned_to": "Anna"}, {"task_id": 2, "title": "HU Submission", "description": "Dossier preparation for submission in Hungary. Submission expected September 2023.", "status": "In progress", "assigned_to": "Alex"}]}]}